hotworker.py
setup.py
hotworker.egg-info/PKG-INFO
hotworker.egg-info/SOURCES.txt
hotworker.egg-info/dependency_links.txt
hotworker.egg-info/requires.txt
hotworker.egg-info/top_level.txt